LICENSE
MANIFEST.in
README.md
setup.py
setup_ferris-ef.py
ferris_ef/__init__.py
ferris_ef/base.py
ferris_ef/context.py
ferris_ef.egg-info/PKG-INFO
ferris_ef.egg-info/SOURCES.txt
ferris_ef.egg-info/dependency_links.txt
ferris_ef.egg-info/not-zip-safe
ferris_ef.egg-info/requires.txt
ferris_ef.egg-info/top_level.txt
ferris_ef/__pycache__/__init__.cpython-38.pyc
ferris_ef/__pycache__/base.cpython-38.pyc
ferris_ef/__pycache__/context.cpython-38.pyc
fx_ef/__init__.py
fx_ef/base.py
fx_ef/context.py