Metadata-Version: 2.1
Name: ferris-ef
Version: 1.5.1
Summary: Utilities for working with Ferris Executor Framework
Home-page: https://pypi.org/project/ferris-ef/
Author: Nikola Gajin
Author-email: nikola@ballab.com
License: Apache2.0
Platform: any
Classifier: Development Status :: 3 - Alpha
Classifier: Environment :: Console
Classifier: Intended Audience :: Developers
Classifier: License :: OSI Approved :: GNU General Public License v3 (GPLv3)
Classifier: Operating System :: OS Independent
Classifier: Programming Language :: Python :: 3.6
Classifier: Topic :: System :: Logging
Classifier: Topic :: Software Development :: Libraries :: Python Modules
License-File: LICENSE
